CHANGES.txt
LICENSE.txt
MANIFEST.in
README.txt
setup.py
./pynyol/__init__.py
./pynyol/cleaner.py
./pynyol/dictanum.py
./pynyol/numadict.py
./pynyol/silabizer.py
./pynyol/test/__init__.py
./pynyol/test/test_cleaner.py
./pynyol/test/test_dictanum.py
bin/express_a_num.py
docs/dictanum.txt
pynyol/__init__.py
pynyol/cleaner.py
pynyol/dictanum.py
pynyol/numadict.py
pynyol/silabizer.py
pynyol.egg-info/PKG-INFO
pynyol.egg-info/SOURCES.txt
pynyol.egg-info/dependency_links.txt
pynyol.egg-info/top_level.txt
pynyol/test/__init__.py
pynyol/test/test_cleaner.py
pynyol/test/test_dictanum.py