Metadata-Version: 2.1
Name: pynyol
Version: 0.1.3
Summary: Package aimed at helping with processing the spanish language.
Home-page: https://pypi.org/project/pynyol
Author: Juanma López
Author-email: lopezjuanma96@gmail.com
License: LICENSE.txt
License-File: LICENSE.txt
